column_print.py
column_print-0.3.0.dist-info/LICENSE.txt
column_print-0.3.0.dist-info/WHEEL
column_print-0.3.0.dist-info/METADATA
column_print-0.3.0.dist-info/RECORD
